mlpmixer_flax/__init__.py
mlpmixer_flax/checkpoint.py
mlpmixer_flax/config.py
mlpmixer_flax/dataloader.py
mlpmixer_flax/models.py
mlpmixer_flax/train.py
mlpmixer_flax/train_utils.py
mlpmixer_flax-0.0.1.dist-info/LICENSE
mlpmixer_flax-0.0.1.dist-info/METADATA
mlpmixer_flax-0.0.1.dist-info/WHEEL
mlpmixer_flax-0.0.1.dist-info/top_level.txt
mlpmixer_flax-0.0.1.dist-info/zip-safe
mlpmixer_flax-0.0.1.dist-info/RECORD
