Metadata-Version: 2.1
Name: mlpmixer-flax
Version: 0.0.1
Summary: Flax implementation of MLP-Mixer from MLP-Mixer: An all-MLP Architecture for Vision
Home-page: https://github.com/SauravMaheshkar/MLP-Mixer
Author: Saurav Maheshkar
Author-email: sauravvmaheshkar@gmail.com
License: MIT
Platform: UNKNOWN
Requires-Dist: einops (>=0.3)
Requires-Dist: flax
Requires-Dist: jax
